play_store_scrapper/__init__.py
play_store_scrapper/store.py
play_store_scrapper/internals/__init__.py
play_store_scrapper/internals/elements.py
play_store_scrapper/internals/regex_helper.py
play_store_scrapper-1.0.2.dist-info/LICENSE
play_store_scrapper-1.0.2.dist-info/METADATA
play_store_scrapper-1.0.2.dist-info/WHEEL
play_store_scrapper-1.0.2.dist-info/top_level.txt
play_store_scrapper-1.0.2.dist-info/RECORD
