Metadata-Version: 2.1
Name: play-store-scrapper
Version: 1.0.2
Summary: A python package to scrape data from Google Play Store using Selenium
Home-page: https://github.com/cstayyab/play-store-scrapper
Author: Muhammad Tayyab Sheikh
Author-email: cstayyab@gmail.com
License: UNKNOWN
Platform: UNKNOWN
Classifier: Programming Language :: Python :: 3
Classifier: License :: OSI Approved :: MIT License
Classifier: Operating System :: OS Independent
Requires-Python: >=3.6
Requires-Dist: selenium
Requires-Dist: htmlparser
Requires-Dist: requests
